percent_max_diff/__init__.py
percent_max_diff/percent_max_diff.py
percent_max_diff/pmd_compositional_benchmark.py
percent_max_diff-0.99.1.dist-info/METADATA
percent_max_diff-0.99.1.dist-info/WHEEL
percent_max_diff-0.99.1.dist-info/top_level.txt
percent_max_diff-0.99.1.dist-info/RECORD
