Metadata-Version: 2.1
Name: percent-max-diff
Version: 0.99.1
Summary: Percent Maximum Difference
Home-page: UNKNOWN
Author: Scott Tyler
Author-email: scottyler89@gmail.com
License: UNKNOWN
Platform: UNKNOWN
Classifier: Programming Language :: Python :: 3
Classifier: License :: OSI Approved :: GNU Affero General Public License v3
Classifier: Operating System :: OS Independent
Requires-Dist: numpy (>=1.16.0)
Requires-Dist: scikit-learn
Requires-Dist: h5py (>=2.9.0)
Requires-Dist: matplotlib (>=3.0.2)
Requires-Dist: scipy (>=1.2.0)
Requires-Dist: numba
Requires-Dist: statsmodels
Requires-Dist: pandas
Requires-Dist: ray
